setup.py
datastore/__init__.py
datastore.leveldb.egg-info/PKG-INFO
datastore.leveldb.egg-info/SOURCES.txt
datastore.leveldb.egg-info/dependency_links.txt
datastore.leveldb.egg-info/namespace_packages.txt
datastore.leveldb.egg-info/requires.txt
datastore.leveldb.egg-info/top_level.txt
datastore/leveldb/__init__.py
datastore/leveldb/test.py