Metadata-Version: 1.0
Name: datastore.leveldb
Version: 0.0.1
Summary: leveldb datastore implementation
Home-page: http://github.com/datastore/datastore.leveldb
Author: Juan Batiz-Benet
Author-email: juan@benet.ai
License: MIT License
Keywords: datastore,leveldb
Platform: UNKNOWN
Classifier: Topic :: Database
Classifier: Topic :: Database :: Front-Ends
